dist_meta/__init__.py
dist_meta/_utils.py
dist_meta/distributions.py
dist_meta/entry_points.py
dist_meta/metadata.py
dist_meta/metadata_mapping.py
dist_meta/py.typed
dist_meta/record.py
dist_meta/wheel.py
dist_meta-0.9.0.dist-info/METADATA
dist_meta-0.9.0.dist-info/WHEEL
dist_meta-0.9.0.dist-info/licenses/LICENSE
dist_meta-0.9.0.dist-info/RECORD
