Metadata-Version: 2.4
Name: dist-meta
Version: 0.9.0
Summary: Parse and create Python distribution metadata.
Project-URL: Homepage, https://github.com/repo-helper/dist-meta
Project-URL: Issue Tracker, https://github.com/repo-helper/dist-meta/issues
Project-URL: Source Code, https://github.com/repo-helper/dist-meta
Project-URL: Documentation, https://dist-meta.readthedocs.io/en/latest
Author-email: Dominic Davis-Foster <dominic@davis-foster.co.uk>
License: Copyright (c) 2021 Dominic Davis-Foster
License-File: LICENSE
Keywords: dist-info,metadata,packaging,pypi
Classifier: Development Status :: 4 - Beta
Classifier: Intended Audience :: Developers
Classifier: License :: OSI Approved :: MIT License
Classifier: Operating System :: OS Independent
Classifier: Programming Language :: Python
Classifier: Programming Language :: Python :: 3 :: Only
Classifier: Programming Language :: Python :: 3.6
Classifier: Programming Language :: Python :: 3.7
Classifier: Programming Language :: Python :: 3.8
Classifier: Programming Language :: Python :: 3.9
Classifier: Programming Language :: Python :: 3.10
Classifier: Programming Language :: Python :: 3.11
Classifier: Programming Language :: Python :: 3.12
Classifier: Programming Language :: Python :: Implementation :: CPython
Classifier: Programming Language :: Python :: Implementation :: PyPy
Classifier: Topic :: Software Development :: Libraries :: Python Modules
Classifier: Topic :: System :: Archiving :: Packaging
Classifier: Typing :: Typed
Requires-Python: >=3.6.1
Requires-Dist: domdf-python-tools>=3.1.0
Requires-Dist: handy-archives>=0.1.0
Requires-Dist: packaging>=20.9
